Metadata-Version: 2.1
Name: odoo-addon-agreement_project
Version: 18.0.1.0.0.6
Requires-Python: >=3.10
Requires-Dist: odoo-addon-agreement_legal==18.0.*
Requires-Dist: odoo==18.0.*
Summary: Link projects to an agreement
Home-page: https://github.com/OCA/agreement
License: AGPL-3
Author: Open Source Integrators, Yves Goldberg (Ygol Internetwork), Odoo Community Association (OCA)
Author-email: support@odoo-community.org
Classifier: Programming Language :: Python
Classifier: Framework :: Odoo
Classifier: Framework :: Odoo :: 18.0
Classifier: License :: OSI Approved :: GNU Affero General Public License v3
Classifier: Development Status :: 4 - Beta
